lightlog-0.1.0.dist-info/RECORD
lightlog-0.1.0.dist-info/WHEEL
lightlog-0.1.0.dist-info/METADATA
lightlog-0.1.0.dist-info/licenses/LICENSE
lightlog/decorator.py
lightlog/__init__.py
lightlog/cpplightlog.cpython-38-darwin.so
lightlog/levelsvalue.py
lightlog/pylightlog.py
