Metadata-Version: 2.1
Name: lightlog
Version: 0.1.0
Summary: A lightweight, flexible logging library for Python with a C++ core and support for distributed computing environments
Keywords: logging,debug,development-tools,python,rank-aware-logging,print-redirection,file-logging,console-logging,multi-process,parallel-computing
Author-Email: Misagh Soltani <msoltani@email.sc.edu>
License: MIT License
Classifier: Intended Audience :: Developers
Classifier: Intended Audience :: Science/Research
Classifier: License :: OSI Approved :: MIT License
Classifier: Operating System :: OS Independent
Classifier: Programming Language :: Python
Classifier: Programming Language :: Python :: 3
Classifier: Programming Language :: C++
Classifier: Programming Language :: Python :: 3.8
Classifier: Programming Language :: Python :: 3.9
Classifier: Programming Language :: Python :: 3.10
Classifier: Programming Language :: Python :: 3.11
Classifier: Programming Language :: Python :: 3.12
Classifier: Topic :: Software Development :: Debuggers
Classifier: Topic :: Software Development :: Libraries :: Python Modules
Classifier: Topic :: System :: Distributed Computing
Classifier: Topic :: System :: Logging
Project-URL: Homepage, https://github.com/misaghsoltani/LightLog
Project-URL: Documentation, https://github.com/misaghsoltani/LightLog#readme
Project-URL: Bug tracker, https://github.com/misaghsoltani/LightLog/issues
Requires-Python: >=3.8
